fjaraskupan/__init__.py
fjaraskupan/__main__.py
fjaraskupan-2.3.3.dist-info/licenses/LICENSE.txt
fjaraskupan-2.3.3.dist-info/METADATA
fjaraskupan-2.3.3.dist-info/WHEEL
fjaraskupan-2.3.3.dist-info/top_level.txt
fjaraskupan-2.3.3.dist-info/RECORD
