Metadata-Version: 2.4
Name: fjaraskupan
Version: 2.3.3
Summary: A python library for speaking to fjäråskupan
Author: Joakim Plate
License-Expression: MIT
Project-URL: Homepage, https://github.com/elupus/fjaraskupan
Classifier: Development Status :: 4 - Beta
Classifier: Environment :: Console
Classifier: Framework :: AsyncIO
Requires-Python: >=3.10
License-File: LICENSE.txt
Requires-Dist: bleak>=0.19
Requires-Dist: bleak-retry-connector>=4.4.3
Provides-Extra: tests
Requires-Dist: pytest-cov; extra == "tests"
Requires-Dist: pytest-mock; extra == "tests"
Requires-Dist: pytest>3.6.4; extra == "tests"
Dynamic: license-file
